sync_env/__init__.py
sync_env/sync_env.py
sync_env-1.0.5.dist-info/METADATA
sync_env-1.0.5.dist-info/WHEEL
sync_env-1.0.5.dist-info/licenses/LICENSE
sync_env-1.0.5.dist-info/RECORD
