Metadata-Version: 2.1
Name: sync_env
Version: 1.0.5
Summary: environment
Project-URL: Homepage, https://github.com/ichir0roie/python-sync-env
Project-URL: Bug Tracker, https://github.com/ichir0roie/python-sync-env/issues
Author-email: ichir0roioe <ichir0roie@gmail.com>
License-File: LICENSE
Classifier: License :: OSI Approved :: BSD License
Classifier: Programming Language :: Python :: 3
Requires-Python: >=3.9
